Workbook

Sheet Start here
B1: Medicaid What-If Template for Community Health Centers
B2: Version 1.0, prepared 2026-10-22 by Primordial Analytics. Free to use, copy and share. Data vintage: HRSA UDS calendar year 2025. Policy status as of 2026-10-22.
B4: Example numbers are loaded so you can see how it works. They are a hypothetical 10,000-patient center scaled from national averages, not any real center. Replace them with your own.
B6: What it is
B7: A small scenario tool. It takes your count of Medicaid expansion adults (ages 19-64) and asks: if some of them lose coverage under the 2025 federal budget law (H.R. 1, Pub. L. 119-21), work requirements and six-month renewals in particular, how much Medicaid visit revenue would you lose, how many would keep coming as uninsured patients, and how much would sliding-fee collections make back? Every result is a live formula, so change an input and everything updates.
B9: How to use it, in four steps
B10: 1. Open the Inputs sheet. Yellow cells are yours to edit; grey cells are calculated. Start with section 1 and enter your patient counts by coverage group. UDS Table 4 has your totals; your EHR or payer plan codes can split expansion adults (19-64) from other Medicaid.
B11: 2. Still on Inputs, replace the visits and dollar figures in section 2 with your own: visits per patient (UDS Table 5 Line 34, clinic plus virtual visits, divided by your total patients on Table 4), your Medicaid payment per visit (your state rate sheet, or UDS Table 9D Medicaid collections divided by Medicaid visits; Medicaid visit counts come from your billing system, because UDS does not report them), and your sliding-fee collections.
B12: 3. Look at the three scenarios in section 3 (Low, Mid, High: share of expansion adults who lose coverage). Keep our defaults or enter your own. The Mid value is a judgment call, not a published forecast.
B13: 4. Read the Results sheet. Compare Low, Mid and High side by side, and check the small table showing how much the answer moves if the share who keep coming, or your Medicaid revenue per visit, is different. The Sources & assumptions sheet says where every default came from.
B15: What it does NOT do
B16: It is a planning scenario, not a forecast. Nobody knows how many people will lose coverage, and the defaults span a wide range on purpose.
... B26: https://www.primordialanalytics.com/community-health-data-help/

Sheet Inputs
B1: Inputs
B2: Example numbers — replace with your own
B3: Yellow cells are yours to edit. Grey cells are calculated. Percentages are entered as percentages (70% or 0.7).
B5: 1. Patients by coverage group (unique patients in a year)
B6: Medicaid expansion adults, ages 19-64 | C6: 1615 | D6: Example: 34% of Medicaid patients (rough default, low confidence). Pull your real count from your EHR or payer plan code; UDS Table 4 does not split it.
B7: Other Medicaid / CHIP (children, other adults) | C7: 3136 | D7: Example: remaining Medicaid/CHIP patients (4,751 minus expansion adults).
B8: Uninsured | C8: 1721 | D8: Example: 17.21% of patients. UDS Table 4, line 7.
B9: Medicare | C9: 1163 | D9: Example: 11.63% of patients. UDS Table 4, line 9.
B10: Private insurance | C10: 2302 | D10: Example: 23.03% (2,303), less 1 so the groups add to exactly 10,000. UDS Table 4, line 11.
B11: Other public / other | C11: 63 | D11: Example: 0.63% of patients (UDS Table 4, line 10).
B12: Total patients | C12: =SUM(C6:C11) | D12: Calculated. Compare with your UDS Table 4 total.
B14: 2. Visits and money
B15: Average visits per patient, per year | C15: 4.4 | D15: Example: 4.40 = national UDS 2025 total visits (144.1M) divided by patients (32.7M). For your center, take Table 5 Line 34 (clinic plus virtual visits) divided by your total patients on Table 4.
B16: Medicaid revenue per visit ($) | C16: 300 | D16: Example: $300, between Medicare's 2026 FQHC base rate ($208) and a figure derived from UDS ($364). Replace with your state Medicaid PPS rate.
B17: Sliding-fee collection per uninsured visit ($) | C17: 67 | D17: Example: $67 = $296 self-pay collected per uninsured patient divided by 4.40 visits. An upper-bound style average; yours may differ a lot.
B18: Visits by a retained uninsured patient, relative to when insured | C18: 0.7 | D18: Example: 70%. Oregon's Medicaid lottery implies 72%; OCHIN pediatric data show 66% (children, E&M visits).
B19: Share of patients who lose coverage but keep coming | C19: 0.7 | D19: Example: 70%. The weakest-evidence input; no study measures it directly. Best calibrated from your own 2023-25 records.
B20: Total annual revenue, all sources ($) (optional) | C20: 16900000 | D20: Example: $1,691 per patient (UDS 2025 patient collections plus non-patient revenue) x 10,000. Leave 0 to skip the percent-of-revenue line.
B22: 3. Scenarios: share of expansion adults who lose coverage (steady state)
B23: Scenario | C23: Low | D23: Mid | E23: High
B24: Lost to work requirements | C24: 0.1 | D24: 0.2 | E24: 0.35 | F24: 10% / 20% / 35%. Mid is a judgment call. Nebraska's early data: 7% at renewal; CMS projects 15%; Urban Institute's range tops out near 38%.
B25: Added loss from six-month renewals | C25: 0.035 | D25: 0.08 | E25: 0.15 | F25: 3.5% / 8% / 15%. CBO's 0.7M (2034) and Urban's 2-3.1M, both shown against Urban's 18.4M 2028 baseline (mixed sources, rough).
B26: Cap on combined loss | C26: 0.5 | D26: Urban's worst case is about 54%; we cap at 50%.
B27: Combined share losing coverage (used in Results) | C27: =MIN(C24+C25,$C$26) | D27: =MIN(D24+D25,$C$26) | E27: =MIN(E24+E25,$C$26)
B28: 2027 partial-year factor (share of steady-state effect in 2027) | C28: 0.7 | D28: CMS projects 2.3M fewer enrollees in FY2027 vs about 3.2M later (72%). A center's first full year is 2028.

Sheet Results
B1: Results: annual effect of expansion adults losing Medicaid
B2: Planning scenarios, not a forecast. Steady-state year (2028 on) unless noted. Everything here is a formula; change Inputs to update.
B3: =IF(AND(Inputs!C6=1615,Inputs!C7=3136,Inputs!C8=1721,Inputs!C9=1163,Inputs!C10=2302,Inputs!C11=63),"Showing the example numbers. Replace them on the Inputs sheet.","")
C4: Low | D4: Mid | E4: High | F4: How it is calculated
B5: Expansion adults on Medicaid today | C5: =Inputs!$C$6 | D5: =Inputs!$C$6 | E5: =Inputs!$C$6 | F5: Inputs, section 1
B6: Share losing coverage | C6: =Inputs!C27 | D6: =Inputs!D27 | E6: =Inputs!E27 | F6: Inputs, section 3 (work requirements plus six-month renewals, capped)
B7: Patients losing coverage | C7: =C5*C6 | D7: =D5*D6 | E7: =E5*E6 | F7: Expansion adults x share losing coverage
B8: ...of whom stay as uninsured patients | C8: =C7*Inputs!$C$19 | D8: =D7*Inputs!$C$19 | E8: =E7*Inputs!$C$19 | F8: Patients losing coverage x share who keep coming
B9: ...of whom stop coming | C9: =C7-C8 | D9: =D7-D8 | E9: =E7-E8 | F9: Patients losing coverage minus those who stay
B10: Lost Medicaid visit revenue ($ per year) | C10: =C7*Inputs!$C$15*Inputs!$C$16 | D10: =D7*Inputs!$C$15*Inputs!$C$16 | E10: =E7*Inputs!$C$15*Inputs!$C$16 | F10: Patients losing coverage x visits per patient x Medicaid revenue per visit
B11: Added sliding-fee revenue ($ per year) | C11: =C8*Inputs!$C$15*Inputs!$C$18*Inputs!$C$17 | D11: =D8*Inputs!$C$15*Inputs!$C$18*Inputs!$C$17 | E11: =E8*Inputs!$C$15*Inputs!$C$18*Inputs!$C$17 | F11: Stayers x visits per patient x relative visit rate x sliding-fee collection per visit
B12: Net revenue change ($ per year) | C12: =C11-C10 | D12: =D11-D10 | E12: =E11-E10 | F12: Added sliding-fee revenue minus lost Medicaid revenue
B13: Net change as a share of total revenue | C13: =IF(Inputs!$C$20>0,C12/Inputs!$C$20,"n/a") | D13: =IF(Inputs!$C$20>0,D12/Inputs!$C$20,"n/a") | E13: =IF(Inputs!$C$20>0,E12/Inputs!$C$20,"n/a") | F13: Net change divided by total annual revenue (Inputs); n/a if left at 0
B14: Net change in 2027 (partial year) ($) | C14: =C12*Inputs!$C$28 | D14: =D12*Inputs!$C$28 | E14: =E12*Inputs!$C$28 | F14: Net change x 2027 partial-year factor
B15: Uninsured share of patients, before | C15: =IF(Inputs!$C$12>0,Inputs!$C$8/Inputs!$C$12,"n/a") | D15: =IF(Inputs!$C$12>0,Inputs!$C$8/Inputs!$C$12,"n/a") | E15: =IF(Inputs!$C$12>0,Inputs!$C$8/Inputs!$C$12,"n/a") | F15: Uninsured patients / total patients
B16: Uninsured share of patients, after | C16: =IF(Inputs!$C$12-C9>0,(Inputs!$C$8+C8)/(Inputs!$C$12-C9),"n/a") | D16: =IF(Inputs!$C$12-D9>0,(Inputs!$C$8+D8)/(Inputs!$C$12-D9),"n/a") | E16: =IF(Inputs!$C$12-E9>0,(Inputs!$C$8+E8)/(Inputs!$C$12-E9),"n/a") | F16: (Uninsured + stayers) / (total patients minus those who stop coming)
B18: Sanity check: revenue from a retained uninsured patient as a share of a Medicaid patient's | C18: =IF(Inputs!$C$16>0,(Inputs!$C$18*Inputs!$C$17)/Inputs!$C$16,"n/a") | D18: =IF(ISNUMBER(C18),IF(C18>0.2,"Check: over 20%","OK"),"n/a") | F18: Nationally, self-pay collections per uninsured patient are about 18% of Medicaid collections per patient. Much higher is worth a second look.
B20: What moves the answer (Mid scenario, net revenue change per year)
C21: Lower | D21: Your input | E21: Higher
B22: If the share who keep coming is... | C22: 0.5 | D22: =Inputs!C19 | E22: 0.85 | F22: 50% and 85% bracket our 70% default (weakest-evidence input).
B23: If Medicaid revenue per visit is ($)... | C23: 208 | D23: =Inputs!C16 | E23: 364 | F23: $208 = Medicare FQHC base rate 2026; $364 = derived from UDS 2025 (Medicaid collections per patient / 4.40 visits).
B24: Net change at that share who keep coming | C24: =$D$7*Inputs!$C$15*(C22*Inputs!$C$18*Inputs!$C$17-Inputs!$C$16) | D24: =$D$7*Inputs!$C$15*(D22*Inputs!$C$18*Inputs!$C$17-Inputs!$C$16) | E24: =$D$7*Inputs!$C$15*(E22*Inputs!$C$18*Inputs!$C$17-Inputs!$C$16)
B25: Net change at that Medicaid revenue per visit | C25: =$D$7*Inputs!$C$15*(Inputs!$C$19*Inputs!$C$18*Inputs!$C$17-C23) | D25: =$D$7*Inputs!$C$15*(Inputs!$C$19*Inputs!$C$18*Inputs!$C$17-D23) | E25: =$D$7*Inputs!$C$15*(Inputs!$C$19*Inputs!$C$18*Inputs!$C$17-E23)
B27: Chart data (feeds the chart below)
C28: Low | D28: Mid | E28: High
B29: Lost Medicaid revenue | C29: =-C10 | D29: =-D10 | E29: =-E10
B30: Added sliding-fee revenue | C30: =C11 | D30: =D11 | E30: =E11
B31: Net change | C31: =C12 | D31: =D12 | E31: =E12

Sheet Sources & assumptions
B1: Sources & assumptions
B2: Data vintage: HRSA UDS calendar year 2025 (data.hrsa.gov). Policy status checked 2026-10-22. Dates in the Date column are the source's date or when we retrieved it.
B4: A. Defaults used on the Inputs sheet
B5: Input | C5: Default | D5: Source | E5: URL | F5: Date | G5: Note
B6: Example center size | C6: 10,000 patients | D6: Hypothetical | F6: 2026-10-22 | G6: A round number so the scaling is easy to follow. Not a real center.
B7: Payer mix (example patients by coverage) | C7: Medicaid (line 8) 47.51%, uninsured 17.21%, Medicare 11.63%, private 23.03%, other public 0.63% | D7: HRSA UDS 2025 Table 4 (national; 32,746,392 patients) | E7: https://data.hrsa.gov/topics/healthcenters/uds/overview/national/table?tableName=4&year=2025 | F7: 2026-05-07 (HRSA refresh) | G7: Each share x 10,000, rounded; private reduced by 1 so the groups sum to 10,000. The 47.51% is Table 4 line 8 (Medicaid, including CHIP-Medicaid). HRSA's headline 47.92% Medicaid/CHIP also adds line 10b (other CHIP), which we leave out of the example. The 32,746,392 patients is HRSA's published national total; summing the awardee-level file, as our worked example does, gives 32,746,371 because some cells are blank.
B8: Expansion adults as a share of Medicaid patients | C8: 34% (1,615 of 4,751) | D8: Primordial Analytics assumption, no published source | E8: https://www.commonwealthfund.org/blog/2025/community-health-center-patients-medicaid-coverage-work-requirements | F8: 2025-05-30 | G8: Our rough placeholder; replace it with your EHR count. For scale only: the Commonwealth Fund (from 2023 UDS) counts about 8.8M working-age adult Medicaid patients nationally, 7.7M of them in expansion states, out of roughly 15.4M Medicaid patients. That is an upper bound for expansion adults (about half), because some adults in expansion states are not in the expansion group. UDS Table 4 does not split Medicaid by expansion status.
B9: Average visits per patient | C9: 4.40 | D9: HRSA UDS 2025 Table 5 (national) | E9: https://data.hrsa.gov/topics/healthcenters/uds/overview/national/table?tableName=5&year=2025 | F9: 2026-05-07 (HRSA refresh) | G9: 144,103,619 visits (125,120,071 clinic + 18,983,548 virtual) / 32,746,392 patients. Medical care alone is 3.34 visits per medical patient. We assume Medicaid and uninsured patients use average visits, which may not hold.
B10: Medicaid revenue per visit | C10: $300 | D10: Judgment within a sourced range | E10: https://data.hrsa.gov/topics/healthcenters/uds/overview/national/table?tableName=9D&year=2025 | F10: 2026-05-07 (HRSA refresh) | G10: Range: $208 (Medicare FQHC PPS base rate, CY2026, before geographic adjustment; CMS MM14309); about $291 (all-payer collections per visit, our calculation); about $364 (Medicaid collections $24.91B / 15.56M Medicaid patients = $1,601 per patient, / 4.40 visits). Medicaid PPS rates are set per center and state: replace with yours.
B11: Sliding-fee collection per uninsured visit | C11: $67 | D11: HRSA UDS 2025 Table 9D (national self-pay line) | E11: https://data.hrsa.gov/topics/healthcenters/uds/overview/national/table?tableName=9D&year=2025 | F11: 2026-05-07 (HRSA refresh) | G11: Self-pay collected $1.668B / 5,634,840 uninsured patients = $296 per patient per year; / 4.40 visits = $67. Upper-bound style figure: HRSA's self-pay line also includes copays owed by insured patients. Collections were 23.7% of gross charges (57.9% of charges after sliding discounts).
B12: Visit rate of a retained uninsured patient vs insured | C12: 70% | D12: Oregon Medicaid lottery, 108 OCHIN health centers (Annals of Family Medicine 13(4):312); OCHIN pediatric patients, Acad Pediatr 2026;26(4):103263 (children, not adults) | E12: https://www.annfammed.org/content/13/4/312 | F12: 2015-07-01 | G12: Gaining Medicaid raised primary-care visits 39% (rate ratio 1.39), so uninsured patients visit about 1/1.39 = 72% as often. OCHIN children who lost coverage had 0.66x the evaluation-and-management visits and 0.41x the preventive visits (Bensken et al., Acad Pediatr 2026, PMID 41730330). 70% is rounded from these; the second study is about children.
B13: Share of patients who lose coverage but keep coming | C13: 70% | D13: Judgment; weakest evidence in the workbook (no direct study) | E13: https://jamanetwork.com/journals/jama-health-forum/fullarticle/2813507 | F13: 2024-01-05 | G13: No published study measures this. Rough triangulation only: in OCHIN (Bensken et al., JAMA Health Forum 2024;5(1):e234622), 16.7% of adult Medicaid patients (96,189 of 575,170) were seen uninsured in the six months after continuous enrollment ended (Apr-Sep 2023); the NACHC/GWU survey (fielded Jan-Feb 2024, released April 2024) had centers reporting that nearly one in four patients were disenrolled. The two measure different things in different populations and time windows, so we do not combine them into a ratio. For comparison, the Commonwealth Fund (2025) assumes 65% of disenrolled patients continue to seek health center care as uninsured patients; this is an assumption in their model, not a measured result. Calibrate from your own 2023-25 records: of patients whose payer changed from Medicaid to self-pay, what share had a visit in the next 12 months?
B14: Total annual revenue (optional) | C14: $16,900,000 | D14: HRSA UDS 2025 Tables 9D and 9E (national) | E14: https://data.hrsa.gov/topics/healthcenters/uds/overview/national/table?tableName=9E&year=2025 | F14: 2026-05-07 (HRSA refresh) | G14: Patient collections $41.88B + non-patient revenue $13.48B = $55.36B / 32,746,392 patients = $1,691 per patient x 10,000. Medicaid is about 45% of total revenue nationally (consistent with the Commonwealth Fund's 43%), so with $300 per visit the example's Medicaid share is a bit lower than national.
B15: Share lost to work requirements: Low 10% / Mid 20% / High 35% | C15: 10% / 20% / 35% | D15: Nebraska (KFF); CMS impact analysis; Urban Institute/RWJF; CBO | E15: https://www.kff.org/medicaid/early-medicaid-work-requirement-insights-from-nebraska/ | F15: 2026-09-29 | G15: Mid is a judgment call. Nebraska's first data: 7% of renewing enrollees subject to the rule lost coverage, 14% of applications subject to the rule denied (draft state minutes; early; exemptions were self-attested). CMS impact analysis (CMS-2454-IFC, 2026-06-01): 15% disenrolled. Urban/RWJF (2026-03-27): 3-7M of 18.4M enrollees in 2028, about 16-38% (our arithmetic on their totals). CBO (2025-08-11, via Georgetown CCF) puts the work requirement at 5.3M more uninsured in 2034 under the enacted law; it gives no expansion-adult base, so we compute no percentage from it. Arkansas 2018: about 16% of those subject, a rough proxy from KFF data (18,164 lost coverage in 2018; 116,229 subject in Feb 2019; mismatched years). These percentages are our arithmetic, not official rates.
B16: Added loss from six-month renewals: Low 3.5% / Mid 8% / High 15% | C16: 3.5% / 8% / 15% | D16: CBO (2025-08-11); Urban Institute/RWJF (2026-03-27) | E16: https://ccf.georgetown.edu/2025/08/14/new-cbo-health-coverage-estimates-of-budget-reconciliation-law/ | F16: 2025-08-14 | G16: CBO: 0.7M more uninsured in 2034 from more frequent redeterminations for expansion adults; relative to Urban's 18.4M 2028 baseline that is 3.8% (mixed sources, rough), rounded down to 3.5%. Urban: 2-3.1M of 18.4M, about 11-17%. Mid is our judgment. Health center patients may differ from all expansion adults both ways: more are medically frail (lowers loss) but more face housing, language and paperwork barriers (raises it). OCHIN found heavier prior users and patients with HIV or substance use disorder were more likely to be disenrolled.
B17: Cap on combined loss | C17: 50% | D17: Urban Institute/RWJF (2026-03-27) | E17: https://www.healthcaredive.com/news/10-million-lose-medicaid-work-requirements-eligibility-checks-urban-institute-robert-wood-johnson/815886/ | F17: 2026-03-27 | G17: Urban's worst case: about 10M of 18.4M, 54%. Combined work-requirement and renewal effects overlap, so we cap rather than add without limit.
B18: 2027 partial-year factor | C18: 70% | D18: CMS impact analysis (CMS-2454-IFC) | E18: https://www.federalregister.gov/documents/2026/06/03/2026-11094/medicaid-program-community-engagement-requirement-for-certain-individuals | F18: 2026-06-01 | G18: CMS projects about 2.3M fewer enrollees in FY2027 and 3.1-3.3M a year after: 2.3 / 3.2 = 72%. Renewals are spread over the year, so a center's first full-year effect is 2028.
B20: B. Key dates and policy status (as of 2026-10-22)
B21: Item | C21: Date | D21: Source | E21: URL | F21: As of | G21: Note
B22: Law: H.R. 1 (Pub. L. 119-21) | C22: 2025-07-04 | D22: Congress.gov / CMS | E22: https://www.cms.gov/newsroom/fact-sheets/medicaid-community-engagement-requirement-certain-individuals-interim-final-rule-comment-period-cms | F22: 2026-06-01 | G22: Sec. 71119 work requirement: 80 hours a month of work, community service, a work program or half-time school, or income of at least $580 a month in 2026. Applies to expansion adults 19-64 not on Medicare.
B23: CMS interim final rule (91 FR 33348, CMS-2454-IFC) | C23: Issued 2026-06-01; Federal Register 2026-06-03 | D23: CMS fact sheet | E23: https://www.cms.gov/newsroom/fact-sheets/medicaid-community-engagement-requirement-certain-individuals-interim-final-rule-comment-period-cms | F23: 2026-06-01 | G23: Effective 2026-07-31; comments closed 2026-07-31. Includes a narrowed medically-frail exemption, 30 days' notice before disenrollment, and a rule that states check existing data first.
B24: Work requirement: state start deadline | C24: 2027-01-01 | D24: CMS fact sheet | E24: https://www.cms.gov/newsroom/fact-sheets/medicaid-community-engagement-requirement-certain-individuals-interim-final-rule-comment-period-cms | F24: 2026-06-01 | G24: States may start earlier. Nebraska began on 2026-05-01 (KFF, 2026-09-29: https://www.kff.org/medicaid/early-medicaid-work-requirement-insights-from-nebraska/).
B25: Good-faith delay (exemption) possible | C25: Expires no later than 2028-12-31 | D25: Federal Register, 91 FR 33348, 42 CFR 435.560(c); Healthcare Dive for the governors' letter | E25: https://www.federalregister.gov/documents/2026/06/03/2026-11094/medicaid-program-community-engagement-requirement-for-certain-individuals | F25: 2026-10-22 | G25: CMS says it expects to approve initial requests for no longer than 6 months, with extensions possible until 2028-12-31, and it expects about 10 states to apply and about 2 to be approved. We found no approved delay as of 2026-10-22. Five governors (Oregon, California, Maine, New Mexico, Virginia) asked HHS in a letter reported 2026-10-02 to delay the 2027-01-01 compliance date (Healthcare Dive: https://www.healthcaredive.com/news/medicaid-work-requirements-governors-ask-hhs-delay-letter/831992/). Recheck before relying on a start date.
B26: Litigation | C26: Filed 2026-06-29 | D26: Healthcare Dive | E26: https://www.healthcaredive.com/news/judge-rejects-states-bid-pause-medicaid-work-requirements/826714/ | F26: 2026-07-31 | G26: 25 states and DC sued in federal court in Massachusetts. About 2026-07-30 the judge denied a preliminary injunction without prejudice; the rule stays in effect while expedited merits briefing continues. We found no later ruling as of 2026-10-22.
B27: Six-month renewals for expansion adults | C27: Renewals scheduled on or after 2027-01-01 | D27: Georgetown CCF on CMS SMD #26-001 (2026-03-06) | E27: https://ccf.georgetown.edu/2026/03/06/cms-releases-guidance-on-6-month-medicaid-renewals-for-expansion-adults/ | F27: 2026-03-06 | G27: Starts 2027-01-01 and rolls through 2027. Other Medicaid groups stay on 12-month renewals.
B28: Retroactive coverage shortened (not modeled) | C28: Applications on or after 2027-01-01 | D28: NAMD OBBBA timeline | E28: https://digitalgovernmenthub.org/wp-content/uploads/2025/09/OBBBA-Medicaid-Policy-Timeline-08-12-25.pdf | F28: 2025-08-12 | G28: From up to 3 months to 1 month for expansion adults and 2 months for others. Could reduce revenue on care given before enrollment; not in this template.
B29: Cost sharing (not modeled) | C29: 2028-10-01 | D29: National Health Law Program FAQ | E29: https://healthlaw.org/wp-content/uploads/2026/03/McKee-FAQs-OBBBA-Cost-Sharing-03192026.pdf | F29: 2026-03-19 | G29: Applies to expansion adults above 100% FPL, up to $35 per service. FQHC, primary care and behavioral health services are exempt, so no direct revenue effect on health centers is expected.
B31: C. Limits to keep in mind
B32: - Scenario tool, not a forecast. The policy is in flux: litigation is pending, we found no approved state delay as of 2026-10-22, and Nebraska's numbers are early and come from draft minutes.
B33: - We do not know any center's real numbers. Every default is editable, and national averages can differ a lot from your center, especially by state and expansion status.
B34: - Some sources were read through secondary summaries because the primary pages were blocked to us (CBO and the Commonwealth Fund blog). Treat those percentages with extra caution.
B35: - The Commonwealth Fund / Geiger Gibson estimate of up to 5.6M health center patients and $32B in lost revenue (2025-05-30) predates the enacted law, so we did not use it as a default.
